yaml_manager/__init__.py
yaml_manager/file_controller.py
yaml_manager/json_file.py
yaml_manager/yaml_file.py
YamlManager-1.2.4.dist-info/LICENSE
YamlManager-1.2.4.dist-info/METADATA
YamlManager-1.2.4.dist-info/WHEEL
YamlManager-1.2.4.dist-info/top_level.txt
YamlManager-1.2.4.dist-info/RECORD
