Metadata-Version: 2.1
Name: YamlManager
Version: 1.2.4
Summary: A simple package for managing JSON and YAML files
Author-email: Lucas Hix <admin@peng1104.net>
License: Copyright © 2024 Lucas Hix <admin@peng1104.net>
Project-URL: changelog, https://github.com/Peng1104/YamlManager/releases/latest
Project-URL: issues, https://github.com/Peng1104/YamlManager/issues
Project-URL: source, https://github.com/Peng1104/YamlManager
Classifier: License :: OSI Approved :: MIT License
Classifier: Programming Language :: Python :: 3
Classifier: Programming Language :: Python :: 3 :: Only
Classifier: Programming Language :: Python :: 3.9
Classifier: Programming Language :: Python :: 3.10
Classifier: Programming Language :: Python :: 3.11
Classifier: Programming Language :: Python :: 3.12
Classifier: Programming Language :: Python :: 3.13
Classifier: License :: OSI Approved :: MIT License
Classifier: Operating System :: OS Independent
Requires-Python: >=3.9
License-File: LICENSE
Requires-Dist: PyYAML>=5.1
